alicebot/adapter/apscheduler/__init__.py
alicebot/adapter/apscheduler/config.py
alicebot/adapter/apscheduler/event.py
alicebot/adapter/apscheduler/py.typed
alicebot_adapter_apscheduler-0.11.0.dist-info/METADATA
alicebot_adapter_apscheduler-0.11.0.dist-info/WHEEL
alicebot_adapter_apscheduler-0.11.0.dist-info/RECORD
